main.py
agent/__init__.py
agent/clickhouse_agent.py
config/__init__.py
config/settings.py
providers/__init__.py
providers/local_llm.py
providers/openrouter.py
tools/__init__.py
tools/clickhouse_tools.py
tools/data_tools.py
ui/__init__.py
ui/beautiful_interface.py
ui/minimal_interface.py
ui/onboarding.py
ui/settings_manager.py
utils/__init__.py
utils/logging.py
moja_clickhouse_agent-1.0.1.dist-info/METADATA
moja_clickhouse_agent-1.0.1.dist-info/WHEEL
moja_clickhouse_agent-1.0.1.dist-info/entry_points.txt
moja_clickhouse_agent-1.0.1.dist-info/top_level.txt
moja_clickhouse_agent-1.0.1.dist-info/RECORD
