Metadata-Version: 2.4
Name: moja-clickhouse-agent
Version: 1.0.1
Summary: 🚀 ClickHouse AI Agent - Intelligent database analysis and operations
Home-page: https://github.com/vish/moja
Author: Vish
Author-email: vish@example.com
Classifier: Development Status :: 4 - Beta
Classifier: Intended Audience :: Developers
Classifier: Intended Audience :: System Administrators
Classifier: License :: OSI Approved :: MIT License
Classifier: Operating System :: OS Independent
Classifier: Programming Language :: Python :: 3
Classifier: Programming Language :: Python :: 3.8
Classifier: Programming Language :: Python :: 3.9
Classifier: Programming Language :: Python :: 3.10
Classifier: Programming Language :: Python :: 3.11
Classifier: Topic :: Database
Classifier: Topic :: Scientific/Engineering :: Information Analysis
Classifier: Topic :: Software Development :: Libraries :: Python Modules
Requires-Python: >=3.8
Requires-Dist: typer[all]>=0.9.0
Requires-Dist: rich>=13.0.0
Requires-Dist: textual>=0.40.0
Requires-Dist: clickhouse-connect>=0.6.0
Requires-Dist: clickhouse-driver>=0.2.0
Requires-Dist: pandas>=1.5.0
Requires-Dist: numpy>=1.20.0
Requires-Dist: plotly>=5.0.0
Requires-Dist: matplotlib>=3.5.0
Requires-Dist: httpx>=0.24.0
Requires-Dist: requests>=2.28.0
Requires-Dist: python-dotenv>=1.0.0
Requires-Dist: pydantic>=2.0.0
Requires-Dist: aiofiles>=23.0.0
Requires-Dist: orjson>=3.8.0
Requires-Dist: structlog>=23.0.0
Requires-Dist: openai>=1.0.0
Requires-Dist: anthropic>=0.25.0
Provides-Extra: dev
Requires-Dist: pytest>=7.0.0; extra == "dev"
Requires-Dist: pytest-asyncio>=0.21.0; extra == "dev"
Requires-Dist: black>=23.0.0; extra == "dev"
Requires-Dist: isort>=5.12.0; extra == "dev"
Requires-Dist: flake8>=6.0.0; extra == "dev"
Requires-Dist: mypy>=1.0.0; extra == "dev"
Dynamic: author
Dynamic: author-email
Dynamic: classifier
Dynamic: description
Dynamic: description-content-type
Dynamic: home-page
Dynamic: provides-extra
Dynamic: requires-dist
Dynamic: requires-python
Dynamic: summary
